{"assets/data/json/privacy.json":["assets/data/json/privacy.json"],"assets/data/json/rules.json":["assets/data/json/rules.json"],"assets/data/json/terms.json":["assets/data/json/terms.json"],"assets/data/text/privacy.md":["assets/data/text/privacy.md"],"assets/data/text/rules.md":["assets/data/text/rules.md"],"assets/data/text/terms.md":["assets/data/text/terms.md"],"assets/fonts/girl.ttf":["assets/fonts/girl.ttf"],"assets/icons/github.png":["assets/icons/github.png"],"assets/icons/google.png":["assets/icons/google.png"],"assets/icons/instagram.png":["assets/icons/instagram.png"],"assets/icons/msg.png":["assets/icons/msg.png"],"assets/icons/scan.png":["assets/icons/scan.png"],"assets/icons/setting.png":["assets/icons/setting.png"],"assets/icons/share.png":["assets/icons/share.png"],"assets/icons/text.png":["assets/icons/text.png"],"assets/images/empty.png":["assets/images/empty.png"],"assets/images/login.jpg":["assets/images/login.jpg"],"assets/images/login/0.webp":["assets/images/login/0.webp"],"assets/images/login/1.webp":["assets/images/login/1.webp"],"assets/images/login/2.webp":["assets/images/login/2.webp"],"assets/images/login/3.webp":["assets/images/login/3.webp"],"assets/images/login/4.webp":["assets/images/login/4.webp"],"assets/images/login/5.webp":["assets/images/login/5.webp"],"assets/images/scan/photo.png":["assets/images/scan/photo.png"],"assets/images/scan/qrcode.png":["assets/images/scan/qrcode.png"],"assets/images/wechatop.png":["assets/images/wechatop.png"],"assets/raw/logo.ico":["assets/raw/logo.ico"],"assets/raw/logo.png":["assets/raw/logo.png"],"assets/raw/logo.svg":["assets/raw/logo.svg"],"packages/cupertino_icons/assets/CupertinoIcons.ttf":["packages/cupertino_icons/assets/CupertinoIcons.ttf"],"packages/wakelock_web/assets/no_sleep.js":["packages/wakelock_web/assets/no_sleep.js"]}